dj_database_url-stubs/METADATA.toml
dj_database_url-stubs/__init__.pyi
types_dj_database_url-1.3.0.3.dist-info/METADATA
types_dj_database_url-1.3.0.3.dist-info/WHEEL
types_dj_database_url-1.3.0.3.dist-info/top_level.txt
types_dj_database_url-1.3.0.3.dist-info/RECORD
